odoo/addons/ssi_liquidity_transfer/README.rst
odoo/addons/ssi_liquidity_transfer/__init__.py
odoo/addons/ssi_liquidity_transfer/__manifest__.py
odoo/addons/ssi_liquidity_transfer/menu.xml
odoo/addons/ssi_liquidity_transfer/data/approval_template_data.xml
odoo/addons/ssi_liquidity_transfer/data/base_automation_data.xml
odoo/addons/ssi_liquidity_transfer/data/ir_actions_server_data.xml
odoo/addons/ssi_liquidity_transfer/data/ir_sequence_data.xml
odoo/addons/ssi_liquidity_transfer/data/policy_template_data.xml
odoo/addons/ssi_liquidity_transfer/data/res_partner_category_data.xml
odoo/addons/ssi_liquidity_transfer/data/sequence_template_data.xml
odoo/addons/ssi_liquidity_transfer/models/__init__.py
odoo/addons/ssi_liquidity_transfer/models/account_move.py
odoo/addons/ssi_liquidity_transfer/models/account_move_line.py
odoo/addons/ssi_liquidity_transfer/models/liquidity_transfer.py
odoo/addons/ssi_liquidity_transfer/models/liquidity_transfer_type.py
odoo/addons/ssi_liquidity_transfer/security/ir.model.access.csv
odoo/addons/ssi_liquidity_transfer/security/ir_module_category_data.xml
odoo/addons/ssi_liquidity_transfer/security/ir_rule_data.xml
odoo/addons/ssi_liquidity_transfer/security/res_group_data.xml
odoo/addons/ssi_liquidity_transfer/static/description/icon.png
odoo/addons/ssi_liquidity_transfer/views/liquidity_transfer_type_views.xml
odoo/addons/ssi_liquidity_transfer/views/liquidity_transfer_views.xml
odoo14_addon_ssi_liquidity_transfer-14.0.1.7.0.dist-info/METADATA
odoo14_addon_ssi_liquidity_transfer-14.0.1.7.0.dist-info/WHEEL
odoo14_addon_ssi_liquidity_transfer-14.0.1.7.0.dist-info/top_level.txt
odoo14_addon_ssi_liquidity_transfer-14.0.1.7.0.dist-info/RECORD
